{"planets":[{"position":{"x":"160","y":"0"},"diameter":32,"orbitspeed":0.003,"mooncount":2,"moondistance":36,"moondiameter":12,"label":"anonymous"},{"position":{"x":"74","y":"228"},"diameter":32,"orbitspeed":-0.003,"mooncount":3,"moondistance":36,"moondiameter":12,"label":"anonymous"},{"position":{"x":"-453","y":"329"},"diameter":32,"orbitspeed":0.003,"mooncount":5,"moondistance":36,"moondiameter":12,"label":"anonymous"},{"position":{"x":"-582","y":"-423"},"diameter":32,"orbitspeed":-0.003,"mooncount":1,"moondistance":36,"moondiameter":12,"label":"anonymous"},{"position":{"x":"148","y":"-457"},"diameter":32,"orbitspeed":0.003,"mooncount":3,"moondistance":36,"moondiameter":12,"label":"anonymous"}]}